{"objects": [
    {
        "comment": "// the back of the cornell box",
        "type": "plane",
        "normal": [0, 0, 1],
        "dist": 40,
        "material": {
            "color": [1, 1, 1]
        }
    },
    {
        "comment": "// the front of the cornell box",
        "type": "plane",
        "normal": [0, 0, -1],
        "dist": 40,
        "material": {
            "color": [1, 1, 1]
        }
    },
    {
        "comment": "// the right of the cornell box",
        "type": "plane",
        "normal": [1, 0, 0],
        "dist": 40,
        "material": {
            "color": [1, 1, 1]
        }
    },
    {
        "comment": "// the left of the cornell box",
        "type": "plane",
        "normal": [-1, 0, 0],
        "dist": 40,
        "material": {
            "color": [1, 1, 1]
        }
    },
    {
        "comment": "// the top of the cornell box",
        "type": "plane",
        "normal": [0, 1, 0],
        "dist": 35,
        "material": {
            "color": [1, 1, 1]
        }
    },
    {
        "comment": "// the bottom of the cornell box",
        "type": "plane",
        "normal": [0, -1, 0],
        "dist": 30,
        "material": {
            "color": [1, 1, 1]
        }
    },
    {
        "comment": "// the matt sphere",
        "type": "sphere",
        "center": [-4, -22, 20],
        "radius": 8,
        "material": {
            "color": [0.4, 0.2, 0.6]
        }
    },
    {
        "comment": "// the glass sphere",
        "type": "sphere",
        "center": [-20, -2, 15],
        "radius": 8,
        "material": {
            "color": [0.6, 0.4, 1],
            "shininess": 1000,
            "specular": [1, 1, 1],
            "reflectivity": 1,
            "reflectType": "GLASSREFLECT"
        }
    },
    {
        "type": "box",
        "minCorner": [-25, -30, 10],
        "maxCorner": [-15, -10, 20],
        "material": {
            "color": [0.3, 0.6, 0.2]
        }
    }

],

"lights": [
    {
        "pos": [-20, 20, 10],
        "color": [1, 1, 1],
        "intensity": 20,
        "attenuate": 1.5
    },
    {
        "pos": [20, 20, 10],
        "color": [1, 1, 1],
        "intensity": 20,
        "attenuate": 2
    },
    {
        "pos": [-10, 20, -20],
        "color": [1, 1, 1],
        "intensity": 20,
        "attenuate": 1
    },
    {
        "pos": [10, 20, -20],
        "color": [1, 1, 1],
        "intensity": 20,
        "attenuate": 1
    }
]
}
